vminspect/__init__.py
vminspect/comparator.py
vminspect/filesystem.py
vminspect/inspector.py
vminspect/timeline.py
vminspect/usnjrnl.py
vminspect/vtscan.py
vminspect/vulnscan.py
vminspect/winevtx.py
vminspect/winreg.py
vminspect-0.0.22.dist-info/DESCRIPTION.rst
vminspect-0.0.22.dist-info/METADATA
vminspect-0.0.22.dist-info/RECORD
vminspect-0.0.22.dist-info/WHEEL
vminspect-0.0.22.dist-info/entry_points.txt
vminspect-0.0.22.dist-info/metadata.json
vminspect-0.0.22.dist-info/top_level.txt
