Metadata-Version: 2.0
Name: vminspect
Version: 0.0.22
Summary: Virtual Machine disk inspection library
Home-page: https://github.com/noxdafox/vminspect
Author: Matteo Cafasso
Author-email: noxdafox@gmail.com
License: BSD
Keywords: virtualisation inspection disk analysis
Platform: UNKNOWN
Classifier: Programming Language :: Python :: 3
Classifier: Development Status :: 3 - Alpha
Classifier: Intended Audience :: Developers
Classifier: License :: OSI Approved :: BSD License
Classifier: Topic :: Software Development :: Libraries :: Python Modules
Requires-Dist: pebble (>=4.0)
Requires-Dist: python-evtx
Requires-Dist: requests
